{
  "scan_time": "2026-05-05 11:00:39",
  "scan_date": "2026-05-05",
  "total_scanned": 500,
  "matched_strategy1": 12,
  "matched_strategy2": 11,
  "strategy1": [
    {
      "code": "3481",
      "name": "群創",
      "price": 27.25,
      "volume": 486644765,
      "momentum": -0.6431,
      "prev_mom": -0.8837,
      "ts": 25.81,
      "date": "2026-05-05",
      "market": "上市",
      "strategy": 1
    },
    {
      "code": "6770",
      "name": "力積電",
      "price": 55.4,
      "volume": 106153725,
      "momentum": -0.1142,
      "prev_mom": -0.925,
      "ts": 52.43,
      "date": "2026-05-05",
      "market": "上市",
      "strategy": 1
    },
    {
      "code": "2891",
      "name": "中信金",
      "price": 53.5,
      "volume": 56190340,
      "momentum": -1.7584,
      "prev_mom": -1.8651,
      "ts": 52.35,
      "date": "2026-05-05",
      "market": "上市",
      "strategy": 1
    },
    {
      "code": "3715",
      "name": "定穎投控",
      "price": 196.5,
      "volume": 46989008,
      "momentum": -7.415,
      "prev_mom": -8.623,
      "ts": 185.54,
      "date": "2026-05-05",
      "market": "上市",
      "strategy": 1
    },
    {
      "code": "8096",
      "name": "擎亞",
      "price": 96.2,
      "volume": 15313348,
      "momentum": -6.9281,
      "prev_mom": -7.5714,
      "ts": 89.77,
      "date": "2026-05-05",
      "market": "上櫃",
      "strategy": 1
    },
    {
      "code": "8110",
      "name": "華東",
      "price": 49.45,
      "volume": 13917442,
      "momentum": -0.7273,
      "prev_mom": -1.5185,
      "ts": 46.5,
      "date": "2026-05-05",
      "market": "上市",
      "strategy": 1
    },
    {
      "code": "2615",
      "name": "萬海",
      "price": 77.0,
      "volume": 6538281,
      "momentum": -1.887,
      "prev_mom": -2.2882,
      "ts": 75.06,
      "date": "2026-05-05",
      "market": "上市",
      "strategy": 1
    },
    {
      "code": "1319",
      "name": "東陽",
      "price": 76.4,
      "volume": 4326438,
      "momentum": -2.9573,
      "prev_mom": -3.147,
      "ts": 74.08,
      "date": "2026-05-05",
      "market": "上市",
      "strategy": 1
    },
    {
      "code": "6443",
      "name": "元晶",
      "price": 37.5,
      "volume": 2205763,
      "momentum": -0.7326,
      "prev_mom": -1.1866,
      "ts": 35.57,
      "date": "2026-05-05",
      "market": "上市",
      "strategy": 1
    },
    {
      "code": "4142",
      "name": "國光生",
      "price": 18.1,
      "volume": 2079237,
      "momentum": -0.562,
      "prev_mom": -0.6503,
      "ts": 17.66,
      "date": "2026-05-05",
      "market": "上市",
      "strategy": 1
    },
    {
      "code": "5452",
      "name": "佶優",
      "price": 33.5,
      "volume": 1984419,
      "momentum": -0.7733,
      "prev_mom": -0.8086,
      "ts": 31.69,
      "date": "2026-05-05",
      "market": "上櫃",
      "strategy": 1
    },
    {
      "code": "2405",
      "name": "輔信",
      "price": 15.6,
      "volume": 1949078,
      "momentum": -0.2038,
      "prev_mom": -0.2702,
      "ts": 15.09,
      "date": "2026-05-05",
      "market": "上市",
      "strategy": 1
    }
  ],
  "strategy2": [
    {
      "code": "4927",
      "name": "泰鼎-KY",
      "price": 58.7,
      "volume": 30498471,
      "momentum": 8.6451,
      "prev_mom": 8.6024,
      "prev2_mom": 9.3153,
      "change_pct": 9.93,
      "ts": 54.47,
      "date": "2026-05-05",
      "market": "上市",
      "strategy": 2
    },
    {
      "code": "6488",
      "name": "環球晶",
      "price": 666.0,
      "volume": 16319219,
      "momentum": 104.312,
      "prev_mom": 98.9784,
      "prev2_mom": 100.0134,
      "change_pct": 9.9,
      "ts": 621.91,
      "date": "2026-05-05",
      "market": "上櫃",
      "strategy": 2
    },
    {
      "code": "6274",
      "name": "台燿",
      "price": 1220.0,
      "volume": 13562585,
      "momentum": 209.3145,
      "prev_mom": 201.3127,
      "prev2_mom": 201.5843,
      "change_pct": 9.91,
      "ts": 1152.73,
      "date": "2026-05-05",
      "market": "上櫃",
      "strategy": 2
    },
    {
      "code": "6451",
      "name": "訊芯-KY",
      "price": 521.0,
      "volume": 10736928,
      "momentum": 19.7655,
      "prev_mom": 18.8191,
      "prev2_mom": 24.1916,
      "change_pct": 9.92,
      "ts": 483.69,
      "date": "2026-05-05",
      "market": "上市",
      "strategy": 2
    },
    {
      "code": "8215",
      "name": "明基材",
      "price": 28.4,
      "volume": 10629701,
      "momentum": 0.6305,
      "prev_mom": 0.4095,
      "prev2_mom": 0.6604,
      "change_pct": 9.86,
      "ts": 26.8,
      "date": "2026-05-05",
      "market": "上市",
      "strategy": 2
    },
    {
      "code": "4960",
      "name": "誠美材",
      "price": 42.6,
      "volume": 5495981,
      "momentum": 10.9959,
      "prev_mom": 10.9501,
      "prev2_mom": 11.1728,
      "change_pct": 8.95,
      "ts": 39.59,
      "date": "2026-05-05",
      "market": "上市",
      "strategy": 2
    },
    {
      "code": "8155",
      "name": "博智",
      "price": 456.5,
      "volume": 4986362,
      "momentum": 81.0064,
      "prev_mom": 80.1162,
      "prev2_mom": 84.3005,
      "change_pct": 10.0,
      "ts": 427.96,
      "date": "2026-05-05",
      "market": "上櫃",
      "strategy": 2
    },
    {
      "code": "1721",
      "name": "三晃",
      "price": 26.7,
      "volume": 3563140,
      "momentum": 5.1013,
      "prev_mom": 5.0672,
      "prev2_mom": 5.3911,
      "change_pct": 9.88,
      "ts": 24.84,
      "date": "2026-05-05",
      "market": "上市",
      "strategy": 2
    },
    {
      "code": "4541",
      "name": "晟田",
      "price": 51.7,
      "volume": 2985831,
      "momentum": 2.9051,
      "prev_mom": 2.6961,
      "prev2_mom": 2.9788,
      "change_pct": 8.05,
      "ts": 49.62,
      "date": "2026-05-05",
      "market": "上櫃",
      "strategy": 2
    },
    {
      "code": "8210",
      "name": "勤誠",
      "price": 1265.0,
      "volume": 2444374,
      "momentum": 178.7021,
      "prev_mom": 166.1611,
      "prev2_mom": 166.3793,
      "change_pct": 10.0,
      "ts": 1196.31,
      "date": "2026-05-05",
      "market": "上市",
      "strategy": 2
    },
    {
      "code": "8227",
      "name": "巨有科技",
      "price": 173.5,
      "volume": 1868256,
      "momentum": 25.428,
      "prev_mom": 24.1852,
      "prev2_mom": 25.2893,
      "change_pct": 9.81,
      "ts": 162.34,
      "date": "2026-05-05",
      "market": "上櫃",
      "strategy": 2
    }
  ]
}